
  { "stem" : "stori",
    "instances" : 
    [ 
      { "docId" : "gallery",
        "docUri" : "gallery.html",
        "score" : 2,
        "contexts" : 
        [ 
          { "form" : "story",
            "weight" : "1",
            "pos" : 10,
            "context" : "...-NG, XSLT, and HTML to transcribe the short <mark>story<\/mark> Kew Gardens by the English author Virginia Woolf.My role...",
            "in" : 
            [ "ssCtx3",
              "ssCtx2" ] },
          
          { "form" : "story",
            "weight" : "1",
            "pos" : 21,
            "context" : "...Woolf.My role - Transcribing and marking up the short <mark>story<\/mark> by the English author Virginia Woolf in XML. Editing the...",
            "in" : 
            [ "ssCtx3",
              "ssCtx2" ] } ] },
      
      { "docId" : "cv",
        "docUri" : "cv.html",
        "score" : 1,
        "contexts" : 
        [ 
          { "form" : "story",
            "weight" : "1",
            "pos" : 51,
            "context" : "Transcribing and marking up the short <mark>story<\/mark> by the English author Virginia Woolf in XML. Editing the...",
            "in" : 
            [ "ssCtx4",
              "ssCtx2" ] } ] } ] }