
  { "stem" : "xml",
    "instances" : 
    [ 
      { "docId" : "cv",
        "docUri" : "cv.html",
        "score" : 4,
        "contexts" : 
        [ 
          { "form" : "XML",
            "weight" : "1",
            "pos" : 56,
            "context" : "...up the short story by the English author Virginia Woolf in <mark>XML<\/mark>. Editing the scheme file. Transforming XML to HTML in...",
            "in" : 
            [ "ssCtx4",
              "ssCtx2" ] },
          
          { "form" : "XML",
            "weight" : "1",
            "pos" : 61,
            "context" : "...Virginia Woolf in XML. Editing the scheme file. Transforming <mark>XML<\/mark> to HTML in XSLT.",
            "in" : 
            [ "ssCtx4",
              "ssCtx2" ] },
          
          { "form" : "XML",
            "weight" : "1",
            "pos" : 90,
            "context" : "oXygen <mark>XML<\/mark>",
            "in" : 
            [ "ssCtx4",
              "ssCtx1" ] },
          
          { "form" : "XML",
            "weight" : "1",
            "pos" : 108,
            "context" : "<mark>XML<\/mark>",
            "in" : 
            [ "ssCtx4",
              "ssCtx1" ] } ] },
      
      { "docId" : "gallery",
        "docUri" : "gallery.html",
        "score" : 3,
        "contexts" : 
        [ 
          { "form" : "XML",
            "weight" : "1",
            "pos" : 2,
            "context" : "  Using <mark>XML<\/mark>, Relax-NG, XSLT, and HTML to transcribe...",
            "in" : 
            [ "ssCtx3",
              "ssCtx2" ] },
          
          { "form" : "XML",
            "weight" : "1",
            "pos" : 26,
            "context" : "...up the short story by the English author Virginia Woolf in <mark>XML<\/mark>. Editing the scheme file. Transforming XML to HTML in...",
            "in" : 
            [ "ssCtx3",
              "ssCtx2" ] },
          
          { "form" : "XML",
            "weight" : "1",
            "pos" : 31,
            "context" : "...Virginia Woolf in XML. Editing the scheme file. Transforming <mark>XML<\/mark> to HTML in XSLT. GitHub ",
            "in" : 
            [ "ssCtx3",
              "ssCtx2" ] } ] } ] }